workshop_demo/__init__.py
workshop_demo/_constants.py
workshop_demo/_dock_widget.py
workshop_demo/_reader.py
workshop_demo/_version.py
workshop_demo/_writer.py
workshop_demo/napari.yaml
workshop_demo/_tests/__init__.py
workshop_demo/_tests/test_dock_widget.py
workshop_demo/_tests/test_reader.py
workshop_demo/_tests/test_writer.py
workshop_demo-0.0.2.dist-info/LICENSE
workshop_demo-0.0.2.dist-info/METADATA
workshop_demo-0.0.2.dist-info/WHEEL
workshop_demo-0.0.2.dist-info/entry_points.txt
workshop_demo-0.0.2.dist-info/top_level.txt
workshop_demo-0.0.2.dist-info/RECORD
