Metadata-Version: 2.1
Name: workshop-demo
Version: 0.0.2
Summary: A demo napari plugin incorporating reader, writer and dock widget contributions using the new npe2 plugin architecture.
Home-page: https://github.com/DragaDoncila/workshop-demo
Author: Draga Doncila Pop
Author-email: ddoncilapop@contractor.chanzuckerberg.com
License: BSD-3-Clause
Project-URL: Bug Tracker, https://github.com/DragaDoncila/workshop-demo/issues
Project-URL: Documentation, https://github.com/DragaDoncila/workshop-demo#README.md
Project-URL: Source Code, https://github.com/DragaDoncila/workshop-demo
Project-URL: User Support, https://github.com/DragaDoncila/workshop-demo/issues
Platform: UNKNOWN
Classifier: Development Status :: 2 - Pre-Alpha
Classifier: Framework :: napari
Classifier: Intended Audience :: Developers
Classifier: License :: OSI Approved :: BSD License
Classifier: Operating System :: MacOS :: MacOS X
Classifier: Operating System :: POSIX :: Linux
Classifier: Programming Language :: Python
Classifier: Programming Language :: Python :: 3
Classifier: Programming Language :: Python :: 3 :: Only
Classifier: Programming Language :: Python :: 3.7
Classifier: Programming Language :: Python :: 3.8
Classifier: Programming Language :: Python :: 3.9
Classifier: Programming Language :: Python :: 3.10
Classifier: Topic :: Software Development :: Testing
Requires-Python: >=3.7
License-File: LICENSE
Requires-Dist: dask[array]
Requires-Dist: imagecodecs
Requires-Dist: napari
Requires-Dist: napari-plugin-engine (>=0.1.4)
Requires-Dist: npe2
Requires-Dist: numpy
Requires-Dist: scikit-image
Requires-Dist: tifffile
